httpsrv/__init__.py
httpsrv/httpsrv.py
httpsrv-0.1.6.dist-info/DESCRIPTION.rst
httpsrv-0.1.6.dist-info/METADATA
httpsrv-0.1.6.dist-info/RECORD
httpsrv-0.1.6.dist-info/WHEEL
httpsrv-0.1.6.dist-info/metadata.json
httpsrv-0.1.6.dist-info/top_level.txt
